Metadata-Version: 2.1
Name: sopel-spellcheck
Version: 0.0.2
Summary: Spellcheck plugin for Sopel IRC bots
Home-page: https://github.com/sopel-irc/sopel-spellcheck
Author: dgw
Author-email: dgw@technobabbl.es
License: Eiffel Forum License, version 2
Platform: Linux x86
Platform: x86-64
Classifier: Development Status :: 5 - Production/Stable
Classifier: Intended Audience :: Developers
Classifier: Intended Audience :: System Administrators
Classifier: License :: Eiffel Forum License (EFL)
Classifier: License :: OSI Approved :: Eiffel Forum License
Classifier: Operating System :: POSIX :: Linux
Classifier: Programming Language :: Python :: 2.7
Classifier: Programming Language :: Python :: 3.3
Classifier: Programming Language :: Python :: 3.4
Classifier: Programming Language :: Python :: 3.5
Classifier: Programming Language :: Python :: 3.6
Classifier: Programming Language :: Python :: 3.7
Classifier: Topic :: Communications :: Chat :: Internet Relay Chat
Requires-Python: >=2.7, !=3.0.*, !=3.1.*, !=3.2.*, <4
